{
    "1": {
        "headers": ["Row 1", "Row 2", "Row 3", "Row 4", "Row 5"],
        "data": [
            ["Box 1", "Box 2","Box 1", "Box 2","Box 3"],
            ["Box 3", "Box 4","Box 1", "Box 2","Box 3"],
            ["Box 5", "Box 6","Box 1", "Box 2","Box 3"],
            ["Box 7", "Box 8","Box 1", "Box 2","Box 3"],
            ["Box 9", "Box 10","Box 1", "Box 2","Box 3"]
        ]
    },
    "2": {
        "headers": ["Row 1", "Row 2", "Row 3", "Row 4", "Row 5"],
        "data": [
            ["Box 11", "Box 12","Box 1", "Box 2","Box 3"],
            ["Box 13", "Box 14","Box 1", "Box 2","Box 3"],
            ["Box 15", "Box 16","Box 1", "Box 2","Box 3"],
            ["Box 17", "Box 18","Box 1", "Box 2","Box 3"],
            ["Box 19", "Box 20","Box 1", "Box 2","Box 3"]
        ]
    },
    "3": {
        "headers": ["Row 1", "Row 2", "Row 3", "Row 4", "Row 5"],
        "data": [
            ["Box 21", "Box 22","Box 1", "Box 2","Box 3"],
            ["Box 23", "Box 24","Box 1", "Box 2","Box 3"],
            ["Box 25", "Box 26","Box 1", "Box 2","Box 3"],
            ["Box 27", "Box 28","Box 1", "Box 2","Box 3"],
            ["Box 29", "Box 30","Box 1", "Box 2","Box 3"]
        ]
    },
    "4": {
        "headers": ["Row 1", "Row 2", "Row 3", "Row 4", "Row 5"],
        "data": [
            ["Box 31", "Box 32","Box 1", "Box 2","Box 3"],
            ["Box 33", "Box 34","Box 1", "Box 2","Box 3"],
            ["Box 35", "Box 36","Box 1", "Box 2","Box 3"],
            ["Box 37", "Box 38","Box 1", "Box 2","Box 3"],
            ["Box 39", "Box 40","Box 1", "Box 2","Box 3"]
        ]
    },
    "5": {
        "headers": ["Row 1", "Row 2", "Row 3"],
        "data": [
            ["Box 41", "Box 42", "Box 42"],
            ["Box 43", "Box 44", "Box 42"],
            ["Box 45", "Box 46", "Box 42"],
            ["Box 47", "Box 48", "Box 42"],
            ["Box 49", "Box 50", "Box 42"]
        ]
    },
    "6": {
        "headers": ["Row 1", "Row 2", "Row 3"],
        "data": [
            ["Box 51", "Box 52", "Box 42"],
            ["Box 53", "Box 54", "Box 42"],
            ["Box 55", "Box 56", "Box 42"],
            ["Box 57", "Box 58", "Box 42"],
            ["Box 59", "Box 60", "Box 42"]
        ]
    },
    "7": {
        "headers": ["Row 1", "Row 2", "Row 3"],
        "data": [
            ["Box 61", "Box 62", "Box 42"],
            ["Box 63", "Box 64", "Box 42"],
            ["Box 65", "Box 66", "Box 42"],
            ["Box 67", "Box 68", "Box 42"],
            ["Box 69", "Box 70", "Box 42"]
        ]
    },
    "8": {
        "headers": ["Row 1", "Row 2", "Row 3"],
        "data": [
            ["Box 71", "Box 72", "Box 42"],
            ["Box 73", "Box 74", "Box 42"],
            ["Box 75", "Box 76", "Box 42"],
            ["Box 77", "Box 78", "Box 42"],
            ["Box 79", "Box 80", "Box 42"]
        ]
    },
    "9": {
        "headers": ["Row 1", "Row 2", "Row 3"],
        "data": [
            ["Box 81", "Box 82", "Box 42"],
            ["Box 83", "Box 84", "Box 42"],
            ["Box 85", "Box 86", "Box 42"],
            ["Box 87", "Box 88", "Box 42"],
            ["Box 89", "Box 90", "Box 42"]
        ]
    },
    "10": {
        "headers": ["Row 1", "Row 2", "Row 3"],
        "data": [
            ["Box 91", "Box 92", "Box 42"],
            ["Box 93", "Box 94", "Box 42"],
            ["Box 95", "Box 96", "Box 42"],
            ["Box 97", "Box 98", "Box 42"],
            ["Box 99", "Box 100", "Box 42"]
        ]
    },
    "11": {
        "headers": ["Row 1", "Row 2", "Row 3"],
        "data": [
            ["Box 101", "Box 102", "Box 42"],
            ["Box 103", "Box 104", "Box 42"],
            ["Box 105", "Box 106", "Box 42"],
            ["Box 107", "Box 108", "Box 42"],
            ["Box 109", "Box 110", "Box 42"]
        ]
    },
    "12": {
        "headers": ["Row 1", "Row 2", "Row 3"],
        "data": [
            ["Box 111", "Box 112", "Box 42"],
            ["Box 113", "Box 114", "Box 42"],
            ["Box 115", "Box 116", "Box 42"],
            ["Box 117", "Box 118", "Box 42"],
            ["Box 119", "Box 120", "Box 42"]
        ]
    }
}